langmem_cloudflare_vectorize/__init__.py
langmem_cloudflare_vectorize/langmem_vectorize_basestore.py
langmem_cloudflare_vectorize-0.1.0.dist-info/METADATA
langmem_cloudflare_vectorize-0.1.0.dist-info/WHEEL
langmem_cloudflare_vectorize-0.1.0.dist-info/RECORD
