Metadata-Version: 2.1
Name: langmem-cloudflare-vectorize
Version: 0.1.0
Summary: Langgraph BaseStore for Vectorize to use with Langmem
Home-page: https://github.com/cloudflare/langchain-cloudflare
License: MIT
Requires-Python: >=3.9,<4.0
Classifier: License :: OSI Approved :: MIT License
Classifier: Programming Language :: Python :: 3
Classifier: Programming Language :: Python :: 3.9
Classifier: Programming Language :: Python :: 3.10
Classifier: Programming Language :: Python :: 3.11
Classifier: Programming Language :: Python :: 3.12
Requires-Dist: httpx (>=0.24.1)
Requires-Dist: langchain-cloudflare (>=0.1.8)
Requires-Dist: langchain-core (>=0.3.60)
Requires-Dist: langgraph (>=0.5.0)
Requires-Dist: pydantic (>=1.10.0,<3.0.0)
Requires-Dist: requests (>=2.31.0)
Project-URL: Repository, https://github.com/cloudflare/langchain-cloudflare
Project-URL: Release Notes, https://github.com/cloudflare/langchain-cloudflare/libs/langmem-cloudflare-vectorize/blob/main/README.md
Project-URL: Source Code, https://github.com/cloudflare/langchain-cloudflare/libs/langmem-cloudflare-vectorize
